yut23_utils/__about__.py
yut23_utils/__init__.py
yut23_utils/_prompt_toolkit_ctrl_bs.py
yut23_utils/fp.py
yut23_utils/ipdb_ctrl_bs.py
yut23_utils/py.typed
yut23_utils/timing.py
yut23_utils-0.2.4.dist-info/METADATA
yut23_utils-0.2.4.dist-info/WHEEL
yut23_utils-0.2.4.dist-info/licenses/LICENSE.txt
yut23_utils-0.2.4.dist-info/RECORD
