Metadata-Version: 2.1
Name: yut23-utils
Version: 0.2.4
Summary: Common code I find myself reaching for from multiple different repositories.
Project-URL: Documentation, https://github.com/yut23/yut23-utils#readme
Project-URL: Issues, https://github.com/yut23/yut23-utils/issues
Project-URL: Source, https://github.com/yut23/yut23-utils
Author-email: yut23 <yut23@gvljohnsons.com>
License-Expression: BSD-3-Clause
License-File: LICENSE.txt
Classifier: Development Status :: 4 - Beta
Classifier: Programming Language :: Python
Classifier: Programming Language :: Python :: 3.9
Classifier: Programming Language :: Python :: 3.10
Classifier: Programming Language :: Python :: 3.11
Classifier: Programming Language :: Python :: 3.12
Classifier: Programming Language :: Python :: Implementation :: CPython
Classifier: Programming Language :: Python :: Implementation :: PyPy
Requires-Python: >=3.9
